TDBRecord/__init__.py
TDBRecord/__main__.py
TDBRecord/command/__init__.py
TDBRecord/command/record.py
TDBRecord/command/server.py
TDBRecord/config/__init__.py
TDBRecord/m3u8/__init__.py
TDBRecord-1.2.2.dist-info/LICENSE
TDBRecord-1.2.2.dist-info/METADATA
TDBRecord-1.2.2.dist-info/WHEEL
TDBRecord-1.2.2.dist-info/entry_points.txt
TDBRecord-1.2.2.dist-info/top_level.txt
TDBRecord-1.2.2.dist-info/RECORD
