Metadata-Version: 2.1
Name: TDBRecord
Version: 1.2.2
Summary: TDB Record Application
Author: onTDB
Author-email: pypi@ontdb.com
Classifier: Programming Language :: Python :: 3
Classifier: License :: OSI Approved :: Apache Software License
Classifier: Operating System :: OS Independent
Requires-Python: >=3.5.0
License-File: LICENSE
Requires-Dist: requests
Requires-Dist: prompt-toolkit
Requires-Dist: streamlink
Requires-Dist: click
